src/__init__.py
src/config.py
src/converter.py
src/database.py
src/http_server.py
src/mcp_server.py
mcp_pg2ck-0.1.4.dist-info/METADATA
mcp_pg2ck-0.1.4.dist-info/WHEEL
mcp_pg2ck-0.1.4.dist-info/entry_points.txt
mcp_pg2ck-0.1.4.dist-info/top_level.txt
mcp_pg2ck-0.1.4.dist-info/RECORD
