Metadata-Version: 2.4
Name: mcp-pg2ck
Version: 0.1.4
Summary: An MCP server for synchronizing PostgreSQL tables to ClickHouse databases
Author-email: Ben <ben@example.com>
License-Expression: MIT
Project-URL: Homepage, https://github.com/ben/.open-sources/pg2ck
Project-URL: Repository, https://github.com/ben/.open-sources/pg2ck
Project-URL: Issues, https://github.com/ben/.open-sources/pg2ck/issues
Classifier: Development Status :: 3 - Alpha
Classifier: Intended Audience :: Developers
Classifier: Operating System :: OS Independent
Classifier: Programming Language :: Python :: 3
Classifier: Programming Language :: Python :: 3.8
Classifier: Programming Language :: Python :: 3.9
Classifier: Programming Language :: Python :: 3.10
Classifier: Programming Language :: Python :: 3.11
Requires-Python: >=3.8
Requires-Dist: psycopg2-binary>=2.9.9
Requires-Dist: clickhouse-connect>=0.5.25
Requires-Dist: python-dotenv>=1.0.1
Requires-Dist: mcp>=1.0.0
Requires-Dist: pydantic>=2.0.0
Requires-Dist: fastapi>=0.104.0
Requires-Dist: uvicorn>=0.24.0
Requires-Dist: starlette>=0.27.0
Provides-Extra: dev
Requires-Dist: pytest>=7.0.0; extra == "dev"
Requires-Dist: pytest-asyncio>=0.21.0; extra == "dev"
Requires-Dist: black>=23.0.0; extra == "dev"
Requires-Dist: isort>=5.12.0; extra == "dev"
Requires-Dist: mypy>=1.0.0; extra == "dev"
